{
    "tokens": [
        "<|endoftext|>",
        "<",
        "issue",
        "_",
        "start",
        "><",
        "issue",
        "_",
        "comment",
        ">",
        "Title",
        ":",
        " `",
        "Z",
        "en",
        "ith",
        "`",
        " working",
        " on",
        " iOS",
        " 12",
        ".",
        "1",
        ".",
        "1",
        "\n",
        "username",
        "_",
        "0",
        ":",
        " `",
        "``",
        "\r",
        "\n",
        "{",
        "\r\n",
        "  ",
        "\"",
        "package",
        "Id",
        "\":",
        " \"",
        "com",
        ".",
        "mu",
        "ire",
        "y",
        "03",
        ".",
        "zen",
        "ith",
        "\",",
        "\r\n",
        "  ",
        "\"",
        "action",
        "\":",
        " \"",
        "working",
        "\",",
        "\r\n",
        "  ",
        "\"",
        "user",
        "Info",
        "\":",
        " {",
        "\r\n",
        "    ",
        "\"",
        "arch",
        "32",
        "\":",
        " false",
        ",",
        "\r\n",
        "    ",
        "\"",
        "package",
        "Id",
        "\":",
        " \"",
        "com",
        ".",
        "mu",
        "ire",
        "y",
        "03",
        ".",
        "zen",
        "ith",
        "\",",
        "\r\n",
        "    ",
        "\"",
        "device",
        "Id",
        "\":",
        " \"",
        "iPhone",
        "8",
        ",",
        "1",
        "\",",
        "\r\n",
        "    ",
        "\"",
        "url",
        "\":",
        " \"",
        "http",
        "://",
        "cy",
        "dia",
        ".",
        "s",
        "aur",
        "ik",
        ".",
        "com",
        "/",
        "package",
        "/",
        "com",
        ".",
        "mu",
        "ire",
        "y",
        "03",
        ".",
        "zen",
        "ith",
        "/",
        "\",",
        "\r\n",
        "    ",
        "\"",
        "iOS",
        "Version",
        "\":",
        " \"",
        "12",
        ".",
        "1",
        ".",
        "1",
        "\",",
        "\r\n",
        "    ",
        "\"",
        "package",
        "Version",
        "Index",
        "ed",
        "\":",
        " true",
        ",",
        "\r\n",
        "    ",
        "\"",
        "package",
        "Name",
        "\":",
        " \"",
        "Z",
        "en",
        "ith",
        "\",",
        "\r\n",
        "    ",
        "\"",
        "category",
        "\":",
        " \"",
        "T",
        "we",
        "aks",
        "\",",
        "\r\n",
        "    ",
        "\"",
        "repository",
        "\":",
        " \"",
        "Char",
        "iz",
        "\",",
        "\r\n",
        "    ",
        "\"",
        "name",
        "\":",
        " \"",
        "Z",
        "en",
        "ith",
        "\",",
        "\r\n",
        "    ",
        "\"",
        "installed",
        "\":",
        " \"",
        "1",
        ".",
        "0",
        ".",
        "6",
        "\",",
        "\r\n",
        "    ",
        "\"",
        "package",
        "Index",
        "ed",
        "\":",
        " true",
        ",",
        "\r\n",
        "    ",
        "\"",
        "package",
        "Status",
        "Ex",
        "plain",
        "ation",
        "\":",
        " \"",
        "This",
        " package",
        " version",
        " has",
        " been",
        " marked",
        " as",
        " Working",
        " based",
        " on",
        " feedback",
        " from",
        " users",
        " in",
        " the",
        " community",
        ".",
        " The",
        " current",
        " positive",
        " rating",
        " is",
        " 100",
        "%",
        " with",
        " 1",
        " working",
        " reports",
        ".\",",
        "\r\n",
        "    ",
        "\"",
        "id",
        "\":",
        " \"",
        "com",
        ".",
        "mu",
        "ire",
        "y",
        "03",
        ".",
        "zen",
        "ith",
        "\",",
        "\r\n",
        "    ",
        "\"",
        "commercial",
        "\":",
        " true",
        ",",
        "\r\n",
        "    ",
        "\"",
        "package",
        "Inst",
        "alled",
        "\":",
        " true",
        ",",
        "\r\n",
        "    ",
        "\"",
        "t",
        "weak",
        "Compat",
        "Version",
        "\":"
    ],
    "values": [
        [
            -0.27895018458366394,
            -0.004106779117137194,
            0.034181296825408936,
            -0.27895018458366394,
            -0.12014696002006531
        ],
        [
            -0.301621675491333,
            -0.010308009572327137,
            0.08038198947906494,
            -0.301621675491333,
            -0.1282377988100052
        ],
        [
            -1.0000000116860974e-07,
            0.02472703345119953,
            -0.08984488993883133,
            -1.1120281219482422,
            -0.2752191424369812
        ],
        [
            -1.0296363830566406,
            -0.061590682715177536,
            0.22731083631515503,
            -1.0296363830566406,
            -0.27095356583595276
        ],
        [
            -1.0000000116860974e-07,
            0.06982121616601944,
            -0.34727588295936584,
            -0.549281120300293,
            -0.20105403661727905
        ],
        [
            -1.0000000116860974e-07,
            -0.004967925604432821,
            -0.044940002262592316,
            0.20096556842327118,
            0.11054573208093643
        ],
        [
            -1.0000000116860974e-07,
            0.059794120490550995,
            -0.22562909126281738,
            -0.9507994055747986,
            -0.26501068472862244
        ],
        [
            -0.7202576398849487,
            -0.01300439890474081,
            0.05515797808766365,
            -0.7202576398849487,
            -0.2357664257287979
        ],
        [
            -0.47648924589157104,
            -0.05097700655460358,
            0.27927371859550476,
            -0.47648924589157104,
            -0.18253420293331146
        ],
        [
            -0.21208280324935913,
            -0.01869368553161621,
            0.19711056351661682,
            -0.21208280324935913,
            -0.09483857452869415
        ],
        [
            -0.3069869875907898,
            -0.0037892728578299284,
            0.02912214584648609,
            -0.3069869875907898,
            -0.1301165372133255
        ],
        [
            -1.0000000116860974e-07,
            -0.0006655683391727507,
            -0.07498729228973389,
            0.01759667880833149,
            0.00887574814260006
        ],
        [
            -1.0000000116860974e-07,
            -0.009725713171064854,
            -0.05693860724568367,
            0.29764804244041443,
            0.1708105206489563
        ],
        [
            -0.29430052638053894,
            -0.0018347757868468761,
            0.014602039940655231,
            -0.29430052638053894,
            -0.125652015209198
        ],
        [
            -0.49613022804260254,
            -0.00937116239219904,
            0.049910131841897964,
            -0.49613022804260254,
            -0.18776072561740875
        ],
        [
            -1.0000000116860974e-07,
            -0.07487865537405014,
            -0.47844693064689636,
            0.2753390371799469,
            0.1565035730600357
        ],
        [
            -0.12052232772111893,
            -0.013447124511003494,
            0.23743845522403717,
            -0.12052232772111893,
            -0.056634146720170975
        ],
        [
            -1.0000000116860974e-07,
            0.0521378330886364,
            0.374957799911499,
            0.24760203063488007,
            0.13904987275600433
        ],
        [
            -1.0000000116860974e-07,
            0.0018053734675049782,
            0.0252473596483469,
            0.1340443193912506,
            0.07150741666555405
        ],
        [
            -1.0000000116860974e-07,
            -0.0014683286426588893,
            -0.029544861987233162,
            0.09489718824625015,
            0.049698274582624435
        ],
        [
            -1.0000000116860974e-07,
            0.036789681762456894,
            -0.3297024369239807,
            -0.25567764043807983,
            -0.11158449947834015
        ],
        [
            -1.0000000116860974e-07,
            -0.027578653767704964,
            -0.3722302317619324,
            0.13859207928180695,
            0.07409030944108963
        ],
        [
            -1.0000000116860974e-07,
            -0.019305061548948288,
            -0.6984012126922607,
            0.05383484438061714,
            0.027641793712973595
        ],
        [
            -1.0000000116860974e-07,
            0.06458879262208939,
            -0.6309100389480591,
            -0.23140282928943634,
            -0.10237400978803635
        ],
        [
            -1.0000000116860974e-07,
            0.04920550435781479,
            -0.43718892335891724,
            -0.25826603174209595,
            -0.11254975199699402
        ],
        [
            -1.0000000116860974e-07,
            -0.0005914965877309442,
            -0.26634839177131653,
            0.004431704990565777,
            0.002220762660726905
        ],
        [
            -1.0000000116860974e-07,
            -0.008442151360213757,
            -0.4157450497150421,
            0.039819467812776566,
            0.02030607871711254
        ],
        [
            -0.3444465100765228,
            -0.029872216284275055,
            0.2091127187013626,
            -0.3444465100765228,
            -0.14285221695899963
        ],
        [
            -1.0000000116860974e-07,
            0.01865294575691223,
            0.21981914341449738,
            0.15735666453838348,
            0.08485587686300278
        ],
        [
            -1.0000000116860974e-07,
            0.0007460647029802203,
            -0.029310651123523712,
            -0.052273355424404144,
            -0.025453707203269005
        ],
        [
            -1.0000000116860974e-07,
            0.003570245811715722,
            -0.0633818581700325,
            -0.11982923001050949,
            -0.056329142302274704
        ],
        [
            -1.0000000116860974e-07,
            -0.00543142668902874,
            -0.2084091454744339,
            0.050831109285354614,
            0.026061365380883217
        ],
        [
            -1.0000000116860974e-07,
            0.06599355489015579,
            -0.29915550351142883,
            -0.6382169723510742,
            -0.22059950232505798
        ],
        [
            -0.29274070262908936,
            -0.02343607135117054,
            0.18734204769134521,
            -0.29274070262908936,
            -0.12509776651859283
        ],
        [
            -1.0000000116860974e-07,
            0.006531045772135258,
            0.028422053903341293,
            0.38599222898483276,
            0.22978796064853668
        ],
        [
            -1.0000000116860974e-07,
            0.13175398111343384,
            -0.6660068035125732,
            -0.5359150171279907,
            -0.1978267878293991
        ],
        [
            -1.0000000116860974e-07,
            0.03498796001076698,
            -0.2529374659061432,
            -0.3309093713760376,
            -0.1383265256881714
        ],
        [
            -1.0000000116860974e-07,
            0.009992895647883415,
            -0.17888742685317993,
            -0.11876726895570755,
            -0.05586136132478714
        ],
        [
            -1.0000000116860974e-07,
            -0.0104982303455472,
            -0.264191210269928,
            0.07654625177383423,
            0.039737243205308914
        ],
        [
            -1.0000000116860974e-07,
            0.12441134452819824,
            -0.5366944670677185,
            -0.6974132061004639,
            -0.23181037604808807
        ],
        [
            -1.0000000116860974e-07,
            -0.013234162703156471,
            -0.38472214341163635,
            0.06658273935317993,
            0.03439927473664284
        ],
        [
            -1.0000000116860974e-07,
            0.04924239218235016,
            -0.3785310387611389,
            -0.30690550804138184,
            -0.13008812069892883
        ],
        [
            -1.0000000116860974e-07,
            0.017768578603863716,
            -0.2873772084712982,
            -0.1324142962694168,
            -0.06183015927672386
        ],
        [
            -1.0000000116860974e-07,
            -0.015768667683005333,
            -0.07427458465099335,
            0.3603664040565491,
            0.2123023420572281
        ],
        [
            -1.0000000116860974e-07,
            -0.049511056393384933,
            -0.31239819526672363,
            0.2784542143344879,
            0.158487007021904
        ],
        [
            -1.0000000116860974e-07,
            0.02753923460841179,
            -0.712343692779541,
            -0.08056356012821198,
            -0.03866003826260567
        ],
        [
            -1.0000000116860974e-07,
            0.13671760261058807,
            -0.6858903169631958,
            -0.5420954823493958,
            -0.19932866096496582
        ],
        [
            -1.0000000116860974e-07,
            0.061573535203933716,
            -0.3855103850364685,
            -0.39736640453338623,
            -0.1597195267677307
        ],
        [
            -1.0000000116860974e-07,
            0.012572098523378372,
            -0.1176810935139656,
            -0.24305789172649384,
            -0.10683193057775497
        ],
        [
            -0.2744513154029846,
            -0.032225146889686584,
            0.27191442251205444,
            -0.2744513154029846,
            -0.1185120940208435
        ],
        [
            -1.0000000116860974e-07,
            -0.013373264111578465,
            -0.5630111694335938,
            0.04642859846353531,
            0.023753106594085693
        ],
        [
            -0.4319792687892914,
            -0.0033388908486813307,
            0.019634727388620377,
            -0.4319792687892914,
            -0.17005027830600739
        ],
        [
            -1.0000000116860974e-07,
            0.051606014370918274,
            -0.3607235848903656,
            -0.34508177638053894,
            -0.14306248724460602
        ],
        [
            -1.0000000116860974e-07,
            0.017825476825237274,
            -0.18485264480113983,
            -0.21612627804279327,
            -0.09643074125051498
        ],
        [
            -0.10131318122148514,
            -0.003769709262996912,
            0.07838424295186996,
            -0.10131318122148514,
            -0.04809269309043884
        ],
        [
            -0.3374292254447937,
            -0.08971526473760605,
            0.6384654641151428,
            -0.3374292254447937,
            -0.14051702618598938
        ],
        [
            -1.0000000116860974e-07,
            0.008206374011933804,
            0.09465712308883667,
            0.16053365170955658,
            0.08669579029083252
        ],
        [
            -1.0000000116860974e-07,
            0.001326322671957314,
            -0.0684797540307045,
            -0.039516888558864594,
            -0.01936809904873371
        ],
        [
            -1.0000000116860974e-07,
            8.049326424952596e-05,
            -0.0005423196125775576,
            -0.3614795506000519,
            -0.14842402935028076
        ],
        [
            -0.5511429905891418,
            -0.008831270039081573,
            0.043828193098306656,
            -0.5511429905891418,
            -0.20149748027324677
        ],
        [
            -1.0000000116860974e-07,
            0.0495680533349514,
            -0.275175541639328,
            -0.46767377853393555,
            -0.18013247847557068
        ],
        [
            -1.0000000116860974e-07,
            0.019327102228999138,
            -0.1857587844133377,
            -0.23574897646903992,
            -0.10404407978057861
        ],
        [
            -0.05504900962114334,
            -0.00031928022508509457,
            0.01192808523774147,
            -0.05504900962114334,
            -0.026767097413539886
        ],
        [
            -1.0000000116860974e-07,
            0.0003989249235019088,
            0.0043966686353087425,
            0.16747556626796722,
            0.09073345363140106
        ],
        [
            -1.0000000116860974e-07,
            -0.1268455535173416,
            -0.4136310815811157,
            0.4938177764415741,
            0.30666351318359375
        ],
        [
            -1.0000000116860974e-07,
            -0.047599758952856064,
            -0.1710750311613083,
            0.4548022150993347,
            0.27823907136917114
        ],
        [
            -1.0000000116860974e-07,
            -0.001758288242854178,
            -0.1281484216451645,
            0.02707493118941784,
            0.013720717281103134
        ],
        [
            -1.0000000116860974e-07,
            0.04635455459356308,
            -0.25253912806510925,
            -0.4802713096141815,
            -0.18355394899845123
        ],
        [
            -1.0000000116860974e-07,
            0.027268683537840843,
            -0.15720289945602417,
            -0.4438306391239166,
            -0.1734617054462433
        ],
        [
            -0.17569705843925476,
            -0.018592266365885735,
            0.23196561634540558,
            -0.17569705843925476,
            -0.08015096187591553
        ],
        [
            -1.0000000116860974e-07,
            0.01875087060034275,
            -0.16853438317775726,
            -0.25480517745018005,
            -0.11125842481851578
        ],
        [
            -1.0000000116860974e-07,
            -0.02806599624454975,
            -0.18164187669754028,
            0.2722049355506897,
            0.15451280772686005
        ],
        [
            -1.0000000116860974e-07,
            0.013662823475897312,
            0.25776737928390503,
            0.10092075169086456,
            0.053004469722509384
        ],
        [
            -1.0000000116860974e-07,
            0.001544108265079558,
            -0.13292036950588226,
            -0.023509928956627846,
            -0.011616791598498821
        ],
        [
            -0.5673473477363586,
            -0.01705266535282135,
            0.08306454867124557,
            -0.5673473477363586,
            -0.2052941471338272
        ],
        [
            -1.0000000116860974e-07,
            0.005852619651705027,
            -0.0344666987657547,
            -0.43113577365875244,
            -0.16980504989624023
        ],
        [
            -1.0000000116860974e-07,
            0.01743762567639351,
            -0.10470274835824966,
            -0.4200238883495331,
            -0.166544109582901
        ],
        [
            -0.191602885723114,
            -0.018006639555096626,
            0.20780529081821442,
            -0.191602885723114,
            -0.08665149658918381
        ],
        [
            -1.0000000116860974e-07,
            -0.0069964914582669735,
            -0.0532735250890255,
            0.23514343798160553,
            0.13133148849010468
        ],
        [
            -1.0000000116860974e-07,
            0.09884677827358246,
            -0.44995731115341187,
            -0.633671760559082,
            -0.21968033909797668
        ],
        [
            -1.0000000116860974e-07,
            -0.007449939846992493,
            -0.33280518651008606,
            0.04381102696061134,
            0.022385288029909134
        ],
        [
            -1.0000000116860974e-07,
            0.04701743274927139,
            -0.34361815452575684,
            -0.32649049162864685,
            -0.13683046400547028
        ],
        [
            -1.0000000116860974e-07,
            0.019775599241256714,
            -0.34511521458625793,
            -0.12204060703516006,
            -0.057301443070173264
        ],
        [
            -1.0000000116860974e-07,
            -0.0014053728664293885,
            -0.00700288824737072,
            0.3430860638618469,
            0.20068475604057312
        ],
        [
            -1.0000000116860974e-07,
            -0.04321569576859474,
            -0.3326433300971985,
            0.23284536600112915,
            0.1299160122871399
        ],
        [
            -1.0000000116860974e-07,
            0.053909361362457275,
            -0.6464707851409912,
            -0.183585062623024,
            -0.0833902508020401
        ],
        [
            -1.0000000116860974e-07,
            0.1417725831270218,
            -0.7067674398422241,
            -0.5473518371582031,
            -0.20059296488761902
        ],
        [
            -1.0000000116860974e-07,
            0.0761333778500557,
            -0.4794960618019104,
            -0.39430055022239685,
            -0.15877790749073029
        ],
        [
            -1.0000000116860974e-07,
            0.017984604462981224,
            -0.1955476850271225,
            -0.20484943687915802,
            -0.09197042882442474
        ],
        [
            -0.22062420845031738,
            -0.01555809285491705,
            0.15844488143920898,
            -0.22062420845031738,
            -0.09819246083498001
        ],
        [
            -1.0000000116860974e-07,
            -0.004870570730417967,
            -0.5185762643814087,
            0.018611211329698563,
            0.009392197243869305
        ],
        [
            -0.34544357657432556,
            -0.0020651747472584248,
            0.014423410408198833,
            -0.34544357657432556,
            -0.14318214356899261
        ],
        [
            -1.0000000116860974e-07,
            0.034254997968673706,
            -0.23360468447208405,
            -0.35596978664398193,
            -0.14663660526275635
        ],
        [
            -1.0000000116860974e-07,
            0.011562895961105824,
            -0.11667616665363312,
            -0.2229575216770172,
            -0.09910246729850769
        ],
        [
            -0.13488641381263733,
            -0.01239495724439621,
            0.1970534324645996,
            -0.13488641381263733,
            -0.06290150433778763
        ],
        [
            -1.0000000116860974e-07,
            0.04853109270334244,
            0.22504788637161255,
            0.3653043210506439,
            0.2156478464603424
        ],
        [
            -1.0000000116860974e-07,
            0.04149578511714935,
            -0.1888098269701004,
            -0.63414067029953,
            -0.21977555751800537
        ],
        [
            -1.0000000116860974e-07,
            -0.02380932681262493,
            -0.2372976690530777,
            0.1838226020336151,
            0.10033527761697769
        ],
        [
            -1.0000000116860974e-07,
            0.0209352970123291,
            -0.24442806839942932,
            -0.18913275003433228,
            -0.08565013855695724
        ],
        [
            -1.0000000116860974e-07,
            -0.018046332523226738,
            -0.1633128970861435,
            0.20089194178581238,
            0.11050157248973846
        ],
        [
            -1.0000000116860974e-07,
            0.06226711720228195,
            -0.3316824734210968,
            -0.4960170388221741,
            -0.18773110210895538
        ],
        [
            -1.0000000116860974e-07,
            0.054247692227363586,
            -0.28440019488334656,
            -0.5076401829719543,
            -0.19074422121047974
        ],
        [
            -0.7371525168418884,
            -0.0008808577549643815,
            0.0036923554725944996,
            -0.7371525168418884,
            -0.23856255412101746
        ],
        [
            -0.5350025296211243,
            -0.01976679638028145,
            0.10003254562616348,
            -0.5350025296211243,
            -0.19760365784168243
        ],
        [
            -1.0000000116860974e-07,
            0.06835649907588959,
            -0.36217257380485535,
            -0.49988389015197754,
            -0.18874013423919678
        ],
        [
            -1.0000000116860974e-07,
            0.018062736839056015,
            -0.14760899543762207,
            -0.2851077616214752,
            -0.12236880511045456
        ],
        [
            -0.1638966202735901,
            -0.018982969224452972,
            0.2522728145122528,
            -0.1638966202735901,
            -0.07524777948856354
        ],
        [
            -1.0000000116860974e-07,
            0.10022987425327301,
            0.43854933977127075,
            0.3841906785964966,
            0.22854867577552795
        ],
        [
            -1.0000000116860974e-07,
            0.0009159226901829243,
            0.002574066398665309,
            0.5592344999313354,
            0.3558271527290344
        ],
        [
            -1.0000000116860974e-07,
            0.0005681123002432287,
            0.0075853317975997925,
            0.14000730216503143,
            0.07489617168903351
        ],
        [
            -1.0000000116860974e-07,
            -0.04070853441953659,
            -0.13126423954963684,
            0.49850863218307495,
            0.3101266026496887
        ],
        [
            -1.0000000116860974e-07,
            0.005504296626895666,
            -0.1084490418434143,
            -0.10725574940443039,
            -0.05075468122959137
        ],
        [
            -1.0000000116860974e-07,
            0.010485094040632248,
            -0.12386654317378998,
            -0.18666881322860718,
            -0.08464831113815308
        ],
        [
            -1.0000000116860974e-07,
            -0.02340579777956009,
            -0.4670889675617218,
            0.09564898908138275,
            0.05010993406176567
        ],
        [
            -1.0000000116860974e-07,
            0.004044075962156057,
            -0.038498405367136,
            -0.2383659929037094,
            -0.10504528880119324
        ],
        [
            -0.09607788920402527,
            -0.00758737837895751,
            0.16590607166290283,
            -0.09607788920402527,
            -0.045732975006103516
        ],
        [
            -1.0000000116860974e-07,
            0.021493542939424515,
            0.09232475608587265,
            0.39036715030670166,
            0.23280367255210876
        ],
        [
            -1.0000000116860974e-07,
            -0.04509300738573074,
            -0.2648670971393585,
            0.2967773675918579,
            0.17024767398834229
        ],
        [
            -0.3527853190898895,
            -0.0036298104096204042,
            0.024930525571107864,
            -0.3527853190898895,
            -0.14559702575206757
        ],
        [
            -0.46598324179649353,
            -0.005673473700881004,
            0.03157754987478256,
            -0.46598324179649353,
            -0.17966794967651367
        ],
        [
            -1.0000000116860974e-07,
            -0.006871629972010851,
            -0.10118478536605835,
            0.12768296897411346,
            0.06791169196367264
        ],
        [
            -1.0000000116860974e-07,
            -0.0018417306710034609,
            -0.7068429589271545,
            0.005197637248784304,
            0.0026055725757032633
        ],
        [
            -1.0000000116860974e-07,
            0.0791037529706955,
            -0.36586833000183105,
            -0.6168663501739502,
            -0.21620824933052063
        ],
        [
            -1.0000000116860974e-07,
            0.032719362527132034,
            -0.49210721254348755,
            -0.14321422576904297,
            -0.06648828089237213
        ],
        [
            -1.0000000116860974e-07,
            -0.03862811625003815,
            -0.11696162819862366,
            0.5255287885665894,
            0.3302631676197052
        ],
        [
            -1.0000000116860974e-07,
            -0.04520495608448982,
            -0.3385199010372162,
            0.2387160211801529,
            0.13353706896305084
        ],
        [
            -1.0000000116860974e-07,
            0.04554849490523338,
            -0.5820906162261963,
            -0.17110200226306915,
            -0.07824983447790146
        ],
        [
            -1.0000000116860974e-07,
            0.13901032507419586,
            -0.6899487376213074,
            -0.5510662198066711,
            -0.2014792114496231
        ],
        [
            -1.0000000116860974e-07,
            0.06816284358501434,
            -0.4469948410987854,
            -0.3741839528083801,
            -0.15249134600162506
        ],
        [
            -1.0000000116860974e-07,
            0.0135475629940629,
            -0.19677433371543884,
            -0.14873751997947693,
            -0.06884822249412537
        ],
        [
            -0.11917088180780411,
            -0.009519025683403015,
            0.16986367106437683,
            -0.11917088180780411,
            -0.05603920668363571
        ],
        [
            -1.0000000116860974e-07,
            -0.0024971435777843,
            -0.49306246638298035,
            0.010078330524265766,
            0.005064558237791061
        ],
        [
            -1.0000000116860974e-07,
            0.01340576633810997,
            -0.16900338232517242,
            -0.173691526055336,
            -0.07932247221469879
        ],
        [
            -0.0159858837723732,
            -0.0008416275959461927,
            0.1061447262763977,
            -0.0159858837723732,
            -0.007929056882858276
        ],
        [
            -1.0000000116860974e-07,
            0.0188155435025692,
            -0.1513437181711197,
            -0.29056641459465027,
            -0.12432325631380081
        ],
        [
            -1.0000000116860974e-07,
            0.0006183728110045195,
            -0.006615845020860434,
            -0.2086193561553955,
            -0.09346845746040344
        ],
        [
            -0.03140516206622124,
            -0.0036285114474594593,
            0.2347634881734848,
            -0.03140516206622124,
            -0.015456030145287514
        ],
        [
            -0.061711158603429794,
            -0.0023606885224580765,
            0.07894272357225418,
            -0.061711158603429794,
            -0.02990381419658661
        ],
        [
            -1.0000000116860974e-07,
            0.020935075357556343,
            -0.08586762845516205,
            -0.770784318447113,
            -0.2438063770532608
        ],
        [
            -1.0000000116860974e-07,
            -0.0039016949012875557,
            -0.2974948585033417,
            0.025895075872540474,
            0.013115167617797852
        ],
        [
            -1.0000000116860974e-07,
            0.0168618094176054,
            -0.34419116377830505,
            -0.10331118851900101,
            -0.048989664763212204
        ],
        [
            -1.0000000116860974e-07,
            0.06926282495260239,
            -0.4705614745616913,
            -0.3576767146587372,
            -0.1471918672323227
        ],
        [
            -1.0000000116860974e-07,
            -0.016870813444256783,
            -0.3266569972038269,
            0.09845133125782013,
            0.0516468770802021
        ],
        [
            -1.0000000116860974e-07,
            0.0444822683930397,
            -0.7237755060195923,
            -0.13155870139598846,
            -0.06145865470170975
        ],
        [
            -1.0000000116860974e-07,
            0.06669872999191284,
            -0.4971209168434143,
            -0.3186991512775421,
            -0.1341700404882431
        ],
        [
            -1.0000000116860974e-07,
            0.06831862032413483,
            -0.3197464942932129,
            -0.6049004197120667,
            -0.2136649489402771
        ],
        [
            -0.5495452880859375,
            -0.010971497744321823,
            0.054552800953388214,
            -0.5495452880859375,
            -0.20111703872680664
        ],
        [
            -1.0000000116860974e-07,
            0.06740602850914001,
            -0.3209782838821411,
            -0.5881379246711731,
            -0.21000182628631592
        ],
        [
            -1.0000000116860974e-07,
            0.02005947008728981,
            -0.1174498200416565,
            -0.4345366358757019,
            -0.1707918345928192
        ],
        [
            -0.43565475940704346,
            -0.02792479284107685,
            0.16319303214550018,
            -0.43565475940704346,
            -0.17111510038375854
        ],
        [
            -1.0000000116860974e-07,
            -0.0002843257097993046,
            -0.006495837587863207,
            0.08401381224393845,
            0.0437704473733902
        ],
        [
            -1.0000000116860974e-07,
            0.029887333512306213,
            -0.11979788541793823,
            -0.8106659054756165,
            -0.24948130548000336
        ],
        [
            -1.0000000116860974e-07,
            0.0238209068775177,
            -0.2345542013645172,
            -0.22928845882415771,
            -0.10155821591615677
        ],
        [
            -1.0000000116860974e-07,
            0.016898617148399353,
            -0.1299821436405182,
            -0.30667370557785034,
            -0.13000722229480743
        ],
        [
            -1.0000000116860974e-07,
            -6.928142829565331e-05,
            -0.31180766224861145,
            0.0004442869976628572,
            0.00022219284437596798
        ],
        [
            -1.0000000116860974e-07,
            0.025057483464479446,
            -0.2636428475379944,
            -0.21260154247283936,
            -0.09504328668117523
        ],
        [
            -1.0000000116860974e-07,
            0.002185023156926036,
            -0.011656980030238628,
            -0.4949188530445099,
            -0.1874433308839798
        ],
        [
            -1.0000000116860974e-07,
            0.03223233297467232,
            -0.21287904679775238,
            -0.37078794836997986,
            -0.1514114886522293
        ],
        [
            -1.0000000116860974e-07,
            0.01845797896385193,
            -0.2113947719335556,
            -0.19324418902397156,
            -0.08731520920991898
        ],
        [
            -1.0000000116860974e-07,
            0.0004923191736452281,
            -0.006707736290991306,
            -0.15948179364204407,
            -0.07339572161436081
        ],
        [
            -1.0000000116860974e-07,
            -0.004636154044419527,
            -0.029415803030133247,
            0.2770739197731018,
            0.15760760009288788
        ],
        [
            -1.0000000116860974e-07,
            0.15636825561523438,
            -0.725597083568573,
            -0.6135194301605225,
            -0.21550287306308746
        ],
        [
            -1.0000000116860974e-07,
            -0.01622004061937332,
            -0.402535617351532,
            0.07758142054080963,
            0.040294673293828964
        ],
        [
            -1.0000000116860974e-07,
            0.09640517830848694,
            -0.5614698529243469,
            -0.4376876950263977,
            -0.17170143127441406
        ],
        [
            -0.2941637933254242,
            -0.013645675033330917,
            0.10864090919494629,
            -0.2941637933254242,
            -0.12560346722602844
        ],
        [
            -0.251224547624588,
            -0.014733427204191685,
            0.13404224812984467,
            -0.251224547624588,
            -0.10991629213094711
        ],
        [
            -1.0000000116860974e-07,
            -0.04451866075396538,
            -0.41254931688308716,
            0.19656527042388916,
            0.1079111248254776
        ],
        [
            -0.5538619756698608,
            -0.019547903910279274,
            0.09670364111661911,
            -0.5538619756698608,
            -0.2021423727273941
        ],
        [
            -1.0000000116860974e-07,
            0.051652852445840836,
            -0.27066850662231445,
            -0.5079914927482605,
            -0.19083435833454132
        ],
        [
            -1.0000000116860974e-07,
            0.01654827408492565,
            -0.17816095054149628,
            -0.2071460336446762,
            -0.09288384765386581
        ],
        [
            -0.16107144951820374,
            -0.010102447122335434,
            0.13640211522579193,
            -0.16107144951820374,
            -0.07406371086835861
        ],
        [
            -0.13321872055530548,
            -0.01913532055914402,
            0.30774518847465515,
            -0.13321872055530548,
            -0.06217910349369049
        ],
        [
            -0.18313269317150116,
            -0.0111786387860775,
            0.13435007631778717,
            -0.18313269317150116,
            -0.08320530503988266
        ],
        [
            -1.0000000116860974e-07,
            0.015748582780361176,
            -0.11054856330156326,
            -0.34325844049453735,
            -0.1424584984779358
        ],
        [
            -1.0000000116860974e-07,
            -0.0008526888559572399,
            -0.028979137539863586,
            0.05721228942275047,
            0.029424231499433517
        ],
        [
            -0.16182878613471985,
            -0.025393376126885414,
            0.3413936495780945,
            -0.16182878613471985,
            -0.0743815153837204
        ],
        [
            -1.0000000116860974e-07,
            0.004568700212985277,
            0.13204191625118256,
            0.06695979088544846,
            0.03460037708282471
        ],
        [
            -0.527362585067749,
            -0.003341295290738344,
            0.01707170531153679,
            -0.527362585067749,
            -0.19572123885154724
        ],
        [
            -1.0000000116860974e-07,
            0.066565603017807,
            -0.3239763081073761,
            -0.5680854320526123,
            -0.2054644078016281
        ],
        [
            -1.0000000116860974e-07,
            0.03194531425833702,
            -0.20535770058631897,
            -0.38392630219459534,
            -0.15555937588214874
        ],
        [
            -0.2980515658855438,
            -0.011560140177607536,
            0.0910390242934227,
            -0.2980515658855438,
            -0.12698005139827728
        ],
        [
            -1.0000000116860974e-07,
            0.0077946060337126255,
            -0.10205862671136856,
            -0.1665920615196228,
            -0.07637380808591843
        ],
        [
            -1.0000000116860974e-07,
            -0.028919577598571777,
            -0.22868451476097107,
            0.22721771895885468,
            0.12646058201789856
        ],
        [
            -1.0000000116860974e-07,
            0.023545438423752785,
            -0.3192846477031708,
            -0.16031105816364288,
            -0.07374434918165207
        ],
        [
            -1.0000000116860974e-07,
            0.01005665771663189,
            -0.06666123867034912,
            -0.3690667748451233,
            -0.15086214244365692
        ],
        [
            -1.0000000116860974e-07,
            0.019649995490908623,
            -0.08728162199258804,
            -0.6612750291824341,
            -0.2251332551240921
        ],
        [
            -0.5320427417755127,
            -0.014279275201261044,
            0.07252876460552216,
            -0.5320427417755127,
            -0.1968774050474167
        ],
        [
            -1.0000000116860974e-07,
            0.04468664526939392,
            -0.23362480103969574,
            -0.509712815284729,
            -0.19127526879310608
        ],
        [
            -1.0000000116860974e-07,
            0.016201376914978027,
            -0.1401083916425705,
            -0.2665972113609314,
            -0.11563459038734436
        ],
        [
            -0.11617835611104965,
            -0.0068525574170053005,
            0.12523265182971954,
            -0.11617835611104965,
            -0.05471861734986305
        ],
        [
            -1.0000000116860974e-07,
            -0.014643462374806404,
            -0.2601330280303955,
            0.10687834769487381,
            0.056292206048965454
        ],
        [
            -1.0000000116860974e-07,
            0.00734240235760808,
            0.05048060044646263,
            0.25784173607826233,
            0.14544998109340668
        ],
        [
            -1.0000000116860974e-07,
            0.009660749696195126,
            -0.12235313653945923,
            -0.17281055450439453,
            -0.0789579227566719
        ],
        [
            -1.0000000116860974e-07,
            0.011159869842231274,
            -0.11428247392177582,
            -0.2192407101392746,
            -0.09765163064002991
        ],
        [
            -1.0000000116860974e-07,
            0.002577541396021843,
            -0.02976524829864502,
            -0.19146494567394257,
            -0.08659566193819046
        ],
        [
            -1.0000000116860974e-07,
            -0.04877251759171486,
            -0.4197421073913574,
            0.21035036444664001,
            0.11619638651609421
        ],
        [
            -0.4892294108867645,
            -0.01790623925626278,
            0.09629913419485092,
            -0.4892294108867645,
            -0.18594393134117126
        ],
        [
            -1.0000000116860974e-07,
            0.04139329120516777,
            -0.2093055248260498,
            -0.5356618762016296,
            -0.19776491820812225
        ],
        [
            -1.0000000116860974e-07,
            0.0025565733667463064,
            -0.02154228277504444,
            -0.2749038636684418,
            -0.11867699027061462
        ],
        [
            -0.1797526776790619,
            -0.021259885281324387,
            0.25983643531799316,
            -0.1797526776790619,
            -0.08182026445865631
        ],
        [
            -0.050847120583057404,
            -0.006370120216161013,
            0.2570945918560028,
            -0.050847120583057404,
            -0.02477733977138996
        ],
        [
            -1.0000000116860974e-07,
            0.0001034855013131164,
            -0.008177042007446289,
            -0.025639915838837624,
            -0.01265561580657959
        ],
        [
            -1.0000000116860974e-07,
            0.020601386204361916,
            -0.16835640370845795,
            -0.2851046621799469,
            -0.12236770242452621
        ],
        [
            -1.0000000116860974e-07,
            0.026747597381472588,
            -0.18171186745166779,
            -0.35769519209861755,
            -0.14719785749912262
        ],
        [
            -0.4681238830089569,
            -0.017290782183408737,
            0.09592349827289581,
            -0.4681238830089569,
            -0.1802559643983841
        ],
        [
            -0.5873585343360901,
            -0.013726668432354927,
            0.06541847437620163,
            -0.5873585343360901,
            -0.20982863008975983
        ],
        [
            -1.0000000116860974e-07,
            0.055058564990758896,
            -0.21912094950675964,
            -0.8241539597511292,
            -0.25127020478248596
        ],
        [
            -1.0000000116860974e-07,
            0.007031591609120369,
            -0.031607791781425476,
            -0.6475669145584106,
            -0.22246386110782623
        ],
        [
            -0.3898266851902008,
            -0.024411115795373917,
            0.15509358048439026,
            -0.3898266851902008,
            -0.15739604830741882
        ],
        [
            -1.0000000116860974e-07,
            0.04765069857239723,
            -0.2905169427394867,
            -0.41155335307121277,
            -0.164020374417305
        ],
        [
            -1.0000000116860974e-07,
            0.013604887761175632,
            -0.10704398900270462,
            -0.29838061332702637,
            -0.1270962357521057
        ],
        [
            -0.23513849079608917,
            -0.023491311818361282,
            0.22629126906394958,
            -0.23513849079608917,
            -0.10381006449460983
        ],
        [
            -1.0000000116860974e-07,
            0.0005138577544130385,
            0.01483409758657217,
            0.06703463941812515,
            0.03464031219482422
        ],
        [
            -1.0000000116860974e-07,
            0.11703439801931381,
            -0.45740190148353577,
            -0.8613276481628418,
            -0.25586774945259094
        ],
        [
            -1.0000000116860974e-07,
            0.08061912655830383,
            -0.3891582489013672,
            -0.5755037069320679,
            -0.20716282725334167
        ],
        [
            -1.0000000116860974e-07,
            -0.005168314557522535,
            -0.2550759017467499,
            0.039734430611133575,
            0.020261868834495544
        ],
        [
            -1.0000000116860974e-07,
            0.03210853785276413,
            -0.26094621419906616,
            -0.28699615597724915,
            -0.12304657697677612
        ],
        [
            -1.0000000116860974e-07,
            0.011275908909738064,
            -0.06502936035394669,
            -0.4436044692993164,
            -0.17339719831943512
        ],
        [
            -1.0000000116860974e-07,
            0.032849352806806564,
            -0.23655365407466888,
            -0.33251067996025085,
            -0.1388663947582245
        ],
        [
            -1.0000000116860974e-07,
            0.015199986286461353,
            -0.20751503109931946,
            -0.1591297835111618,
            -0.07324764132499695
        ],
        [
            -0.08886528015136719,
            -0.002520686713978648,
            0.05936660245060921,
            -0.08886528015136719,
            -0.042459677904844284
        ],
        [
            -1.0000000116860974e-07,
            -0.0006705787382088602,
            -0.005050818435847759,
            0.23746874928474426,
            0.13276635110378265
        ],
        [
            -1.0000000116860974e-07,
            0.07294565439224243,
            -0.3687536418437958,
            -0.5358740091323853,
            -0.19781677424907684
        ],
        [
            -0.03265952318906784,
            -0.003403390757739544,
            0.2118760198354721,
            -0.03265952318906784,
            -0.01606312394142151
        ],
        [
            -1.0000000116860974e-07,
            0.048895906656980515,
            -0.3721943497657776,
            -0.31059426069259644,
            -0.13137197494506836
        ],
        [
            -1.0000000116860974e-07,
            0.005396656226366758,
            -0.03194991126656532,
            -0.42806628346443176,
            -0.16890989243984222
        ],
        [
            -1.0000000116860974e-07,
            0.0017578535480424762,
            -0.14021870493888855,
            -0.0253954716026783,
            -0.012536512687802315
        ],
        [
            -1.0000000116860974e-07,
            0.03705552592873573,
            -0.34489521384239197,
            -0.24466101825237274,
            -0.10743995755910873
        ],
        [
            -1.0000000116860974e-07,
            0.030251100659370422,
            -0.440511018037796,
            -0.1483256220817566,
            -0.06867274641990662
        ],
        [
            -1.0000000116860974e-07,
            -0.018388021737337112,
            -0.3103376626968384,
            0.11221393197774887,
            0.059251658618450165
        ],
        [
            -1.0000000116860974e-07,
            0.010490011423826218,
            -0.06948119401931763,
            -0.3694239556789398,
            -0.1509762704372406
        ],
        [
            -1.0000000116860974e-07,
            0.009303529746830463,
            -0.12013635039329529,
            -0.16915562748908997,
            -0.07744142413139343
        ],
        [
            -1.0000000116860974e-07,
            -0.0003206400142516941,
            -0.026788601651787758,
            0.023658687248826027,
            0.011969270184636116
        ],
        [
            -1.0000000116860974e-07,
            0.009065006859600544,
            0.3739628493785858,
            0.04735953360795975,
            0.024240393191576004
        ],
        [
            -1.0000000116860974e-07,
            0.04545209929347038,
            0.21681226789951324,
            0.3564218282699585,
            0.20963804423809052
        ],
        [
            -0.28209200501441956,
            -0.025836769491434097,
            0.2130289226770401,
            -0.28209200501441956,
            -0.1212829202413559
        ],
        [
            -1.0000000116860974e-07,
            0.1171058714389801,
            -0.5067262053489685,
            -0.6934472918510437,
            -0.231102854013443
        ],
        [
            -1.0000000116860974e-07,
            0.016320044174790382,
            -0.10712748765945435,
            -0.3737140893936157,
            -0.15234225988388062
        ],
        [
            -0.12527868151664734,
            -0.02463497593998909,
            0.41952744126319885,
            -0.12527868151664734,
            -0.058720774948596954
        ],
        [
            -1.0000000116860974e-07,
            0.002108421642333269,
            0.011030317284166813,
            0.3287416696548462,
            0.19114787876605988
        ],
        [
            -1.0000000116860974e-07,
            -0.03202032670378685,
            -0.1592283397912979,
            0.3437027037143707,
            0.20109690725803375
        ],
        [
            -1.0000000116860974e-07,
            0.0029253284446895123,
            0.20707635581493378,
            0.02786540426313877,
            0.014126810245215893
        ],
        [
            -0.08001609146595001,
            -0.0017377124167978764,
            0.04524319991469383,
            -0.08001609146595001,
            -0.03840825706720352
        ],
        [
            -1.0000000116860974e-07,
            0.006271085236221552,
            0.18457309901714325,
            0.06578900665044785,
            0.03397615998983383
        ],
        [
            -1.0000000116860974e-07,
            0.0019763146992772818,
            -0.04703918844461441,
            -0.08788810670375824,
            -0.042014215141534805
        ],
        [
            -1.0000000116860974e-07,
            0.008453281596302986,
            -0.1309857964515686,
            -0.13867118954658508,
            -0.06453586369752884
        ],
        [
            -0.2676366865634918,
            -0.024630865082144737,
            0.21230371296405792,
            -0.2676366865634918,
            -0.11601711809635162
        ],
        [
            -1.0000000116860974e-07,
            -0.011200032196938992,
            -0.05142902210354805,
            0.36843740940093994,
            0.21777649223804474
        ],
        [
            -1.0000000116860974e-07,
            0.00012225205136928707,
            0.04208875447511673,
            0.005792473442852497,
            0.0029046249110251665
        ],
        [
            -1.0000000116860974e-07,
            -0.003937324043363333,
            -0.12756016850471497,
            0.059937119483947754,
            0.030866404995322227
        ],
        [
            -1.0000000116860974e-07,
            0.006532387342303991,
            -0.22121192514896393,
            -0.060914721339941025,
            -0.02952999621629715
        ],
        [
            -1.0000000116860974e-07,
            -0.041259460151195526,
            -0.16243956983089447,
            0.42076098918914795,
            0.2539988160133362
        ],
        [
            -1.0000000116860974e-07,
            0.0033835123758763075,
            -0.34512558579444885,
            -0.01980350911617279,
            -0.00980371329933405
        ],
        [
            -1.0000000116860974e-07,
            0.02540541999042034,
            -0.20249201357364655,
            -0.2937704920768738,
            -0.1254638135433197
        ],
        [
            -0.20693911612033844,
            -0.04734111204743385,
            0.5101322531700134,
            -0.20693911612033844,
            -0.09280164539813995
        ],
        [
            -0.1306174397468567,
            -0.0003486691857688129,
            0.00571124954149127,
            -0.1306174397468567,
            -0.06104954704642296
        ],
        [
            -1.0000000116860974e-07,
            0.013110612519085407,
            -0.062015555799007416,
            -0.5945111513137817,
            -0.21140845119953156
        ],
        [
            -1.0000000116860974e-07,
            0.052050188183784485,
            -0.6166124939918518,
            -0.18609146773815155,
            -0.08441312611103058
        ],
        [
            -1.0000000116860974e-07,
            0.03987402096390724,
            -0.48392432928085327,
            -0.18115900456905365,
            -0.0823972225189209
        ],
        [
            -1.0000000116860974e-07,
            0.006065048277378082,
            -0.1753668189048767,
            -0.0717422217130661,
            -0.03458492457866669
        ],
        [
            -1.0000000116860974e-07,
            0.015006977133452892,
            -0.185820534825325,
            -0.17717590928077698,
            -0.08076059818267822
        ],
        [
            -1.0000000116860974e-07,
            -0.010227827355265617,
            -0.10063005238771439,
            0.18602320551872253,
            0.10163789987564087
        ],
        [
            -1.0000000116860974e-07,
            0.014419895596802235,
            -0.21285907924175262,
            -0.1461484432220459,
            -0.06774386018514633
        ],
        [
            -1.0000000116860974e-07,
            0.005535100121051073,
            -0.28248128294944763,
            -0.03998858109116554,
            -0.019594572484493256
        ],
        [
            -1.0000000116860974e-07,
            -0.0013833874836564064,
            -0.00606832979246974,
            0.3833463788032532,
            0.22796840965747833
        ],
        [
            -1.0000000116860974e-07,
            -0.05135788396000862,
            -0.3310604393482208,
            0.27317965030670166,
            0.15513144433498383
        ],
        [
            -1.0000000116860974e-07,
            0.048517730087041855,
            -0.6543832421302795,
            -0.16125959157943726,
            -0.074142687022686
        ],
        [
            -1.0000000116860974e-07,
            0.12665735185146332,
            -0.7304618954658508,
            -0.44359156489372253,
            -0.17339351773262024
        ],
        [
            -1.0000000116860974e-07,
            0.05600115656852722,
            -0.442812979221344,
            -0.29659974575042725,
            -0.12646684050559998
        ],
        [
            -1.0000000116860974e-07,
            0.01986907236278057,
            -0.23862797021865845,
            -0.1832757592201233,
            -0.0832638069987297
        ],
        [
            -0.19130252301692963,
            -0.012823150493204594,
            0.14819329977035522,
            -0.19130252301692963,
            -0.08652989566326141
        ],
        [
            -1.0000000116860974e-07,
            -0.0035946285352110863,
            -0.5248369574546814,
            0.013605523854494095,
            0.006849038414657116
        ],
        [
            -1.0000000116860974e-07,
            0.0011622172314673662,
            -0.012693649157881737,
            -0.2038169801235199,
            -0.09155895560979843
        ],
        [
            -1.0000000116860974e-07,
            0.03509994223713875,
            -0.25471824407577515,
            -0.3293483257293701,
            -0.13779908418655396
        ],
        [
            -1.0000000116860974e-07,
            0.0009992909617722034,
            -0.013944988138973713,
            -0.15536373853683472,
            -0.07165950536727905
        ],
        [
            -0.16163921356201172,
            -0.019054260104894638,
            0.25644347071647644,
            -0.16163921356201172,
            -0.07430198788642883
        ],
        [
            -0.37987127900123596,
            -0.03634234145283699,
            0.23554912209510803,
            -0.37987127900123596,
            -0.15428774058818817
        ],
        [
            -1.0000000116860974e-07,
            -0.01169847697019577,
            -0.25843197107315063,
            0.08677195757627487,
            0.04526714235544205
        ],
        [
            -1.0000000116860974e-07,
            0.032023780047893524,
            -0.29532840847969055,
            -0.24729032814502716,
            -0.10843446850776672
        ],
        [
            -0.4918588697910309,
            -0.008562073111534119,
            0.045875128358602524,
            -0.4918588697910309,
            -0.18663868308067322
        ],
        [
            -1.0000000116860974e-07,
            0.02910313941538334,
            -0.19142404198646545,
            -0.3727465271949768,
            -0.1520349234342575
        ],
        [
            -1.0000000116860974e-07,
            0.011084403842687607,
            -0.10869347304105759,
            -0.2303771823644638,
            -0.10197856277227402
        ],
        [
            -0.12158466130495071,
            -0.006387282628566027,
            0.1118590459227562,
            -0.12158466130495071,
            -0.05710117146372795
        ],
        [
            -1.0000000116860974e-07,
            -0.015296848490834236,
            -0.09025615453720093,
            0.2955929636955261,
            0.16948260366916656
        ],
        [
            -1.0000000116860974e-07,
            0.18690137565135956,
            -0.6823580265045166,
            -1.0824323892593384,
            -0.2739051580429077
        ],
        [
            -1.0000000116860974e-07,
            0.06026216968894005,
            -0.3130094110965729,
            -0.5146201252937317,
            -0.19252510368824005
        ],
        [
            -1.0000000116860974e-07,
            0.012779123149812222,
            -0.2841982841491699,
            -0.0943816751241684,
            -0.04496551677584648
        ],
        [
            -1.0000000116860974e-07,
            0.031607795506715775,
            -0.2299998551607132,
            -0.3282441198825836,
            -0.1374252885580063
        ],
        [
            -0.39661040902137756,
            -0.0021337736397981644,
            0.013378918170928955,
            -0.39661040902137756,
            -0.1594877541065216
        ],
        [
            -1.0000000116860974e-07,
            0.030071908608078957,
            -0.21891406178474426,
            -0.3280767500400543,
            -0.1373685598373413
        ],
        [
            -1.0000000116860974e-07,
            0.01272027287632227,
            -0.20198653638362885,
            -0.1350582093000412,
            -0.06297584623098373
        ],
        [
            -0.0733649805188179,
            -0.0009671436855569482,
            0.02736877277493477,
            -0.0733649805188179,
            -0.03533748909831047
        ],
        [
            -0.06668523699045181,
            -0.00658603897318244,
            0.2043367326259613,
            -0.06668523699045181,
            -0.032231301069259644
        ],
        [
            -0.33646833896636963,
            -0.04365887492895126,
            0.31141433119773865,
            -0.33646833896636963,
            -0.14019545912742615
        ],
        [
            -1.821326732635498,
            -0.027240902185440063,
            0.10738936066627502,
            -1.821326732635498,
            -0.2536648213863373
        ],
        [
            -0.7794825434684753,
            -0.05023866891860962,
            0.20497730374336243,
            -0.7794825434684753,
            -0.24509380757808685
        ],
        [
            -1.0000000116860974e-07,
            -0.014808283187448978,
            -0.13634634017944336,
            0.19773046672344208,
            0.10860785096883774
        ]
    ],
    "labels": [
        "gate-_in+_hook_pre",
        "hook_post",
        "hook_pre_linear",
        "hook_pre",
        "swish"
    ]
}